libtlda/__init__.py
libtlda/_version.py
libtlda/example.py
libtlda/flda.py
libtlda/iw.py
libtlda/rba.py
libtlda/scl.py
libtlda/suba.py
libtlda/tca.py
libtlda/tcpr.py
libtlda/util.py
libtlda-0.1.5.dist-info/METADATA
libtlda-0.1.5.dist-info/RECORD
libtlda-0.1.5.dist-info/WHEEL
libtlda-0.1.5.dist-info/top_level.txt
