Metadata-Version: 2.1
Name: libtlda
Version: 0.1.5
Summary: Library of transfer learning and domain adaptation                   classifiers.
Home-page: https://github.com/wmkouw/libTLDA
Author: Wouter Kouw
Author-email: wmkouw@gmail.com
License: Apache 2.0
Project-URL: Tracker, https://github.com/wmkouw/libTLDA/issues
Keywords: machine learning,domain adaptation,transfer learning
Platform: UNKNOWN
Classifier: Development Status :: 3 - Alpha
Classifier: License :: OSI Approved :: MIT License
Classifier: Operating System :: POSIX :: Linux
Classifier: Operating System :: MacOS
Classifier: Programming Language :: Python :: 2.7
Classifier: Programming Language :: Python :: 3.4
Classifier: Programming Language :: Python :: 3.5
Classifier: Programming Language :: Python :: 3.6
Classifier: Topic :: Scientific/Engineering :: Artificial Intelligence
Classifier: Topic :: Software Development :: Libraries
Requires-Dist: numpy (>=1.13.3)
Requires-Dist: matplotlib (>=2.0.2)
Requires-Dist: ipython (>=5.5.0)
Requires-Dist: scipy (>=0.11)
Requires-Dist: scikit-learn (>=0.15.0)
Requires-Dist: Keras (>=2.0.0)
Requires-Dist: tensorflow (>=0.12.1)
Requires-Dist: cvxopt (>=1.1.9)
